dynamic_tabs/__init__.py
dynamic_tabs/frontend/build/asset-manifest.json
dynamic_tabs/frontend/build/bootstrap.min.css
dynamic_tabs/frontend/build/index.html
dynamic_tabs/frontend/build/precache-manifest.9de169881986b29b8602b1c99e2c4356.js
dynamic_tabs/frontend/build/service-worker.js
dynamic_tabs/frontend/build/static/css/main.310e05dc.chunk.css
dynamic_tabs/frontend/build/static/css/main.310e05dc.chunk.css.map
dynamic_tabs/frontend/build/static/js/2.945cd767.chunk.js
dynamic_tabs/frontend/build/static/js/2.945cd767.chunk.js.LICENSE.txt
dynamic_tabs/frontend/build/static/js/2.945cd767.chunk.js.map
dynamic_tabs/frontend/build/static/js/main.967eb671.chunk.js
dynamic_tabs/frontend/build/static/js/main.967eb671.chunk.js.map
dynamic_tabs/frontend/build/static/js/runtime-main.11ec9aca.js
dynamic_tabs/frontend/build/static/js/runtime-main.11ec9aca.js.map
streamlit_dynamic_tabs-0.0.3.dist-info/LICENSE
streamlit_dynamic_tabs-0.0.3.dist-info/METADATA
streamlit_dynamic_tabs-0.0.3.dist-info/WHEEL
streamlit_dynamic_tabs-0.0.3.dist-info/top_level.txt
streamlit_dynamic_tabs-0.0.3.dist-info/RECORD
